<annotation>
	<folder>V4 - Renamed B</folder>
	<filename>img-527.png</filename>
	<path>C:\Users\Larkuo\Documents\School\Year 4 Redo\Capstone\Images\V4 - Renamed B\img-527.png</path>
	<source>
		<database>Unknown</database>
	</source>
	<size>
		<width>640</width>
		<height>320</height>
		<depth>3</depth>
	</size>
	<segmented>0</segmented>
	<object>
		<name>chicken</name>
		<pose>Unspecified</pose>
		<truncated>0</truncated>
		<difficult>0</difficult>
		<bndbox>
			<xmin>535</xmin>
			<ymin>134</ymin>
			<xmax>616</xmax>
			<ymax>200</ymax>
		</bndbox>
	</object>
	<object>
		<name>chicken</name>
		<pose>Unspecified</pose>
		<truncated>0</truncated>
		<difficult>0</difficult>
		<bndbox>
			<xmin>435</xmin>
			<ymin>97</ymin>
			<xmax>541</xmax>
			<ymax>156</ymax>
		</bndbox>
	</object>
	<object>
		<name>chicken</name>
		<pose>Unspecified</pose>
		<truncated>0</truncated>
		<difficult>0</difficult>
		<bndbox>
			<xmin>430</xmin>
			<ymin>152</ymin>
			<xmax>532</xmax>
			<ymax>228</ymax>
		</bndbox>
	</object>
	<object>
		<name>potatoe_fries</name>
		<pose>Unspecified</pose>
		<truncated>0</truncated>
		<difficult>0</difficult>
		<bndbox>
			<xmin>79</xmin>
			<ymin>123</ymin>
			<xmax>297</xmax>
			<ymax>274</ymax>
		</bndbox>
	</object>
	<object>
		<name>ketchup_bottle</name>
		<pose>Unspecified</pose>
		<truncated>0</truncated>
		<difficult>0</difficult>
		<bndbox>
			<xmin>338</xmin>
			<ymin>73</ymin>
			<xmax>438</xmax>
			<ymax>251</ymax>
		</bndbox>
	</object>
	<object>
		<name>empty_plate</name>
		<pose>Unspecified</pose>
		<truncated>0</truncated>
		<difficult>0</difficult>
		<bndbox>
			<xmin>251</xmin>
			<ymin>32</ymin>
			<xmax>432</xmax>
			<ymax>105</ymax>
		</bndbox>
	</object>
</annotation>
